gitnextrelease/__init__.py
gitnextrelease/aftermerge.py
gitnextrelease/changelog.py
gitnextrelease/cmds.py
gitnextrelease/common.py
gitnextrelease/config.py
gitnextrelease/fakepr.py
gitnextrelease/feature.py
gitnextrelease/fix.py
gitnextrelease/nextrelease.py
gitnextrelease/versionupdater.py
gitnextrelease-0.7.5.dist-info/LICENSE
gitnextrelease-0.7.5.dist-info/METADATA
gitnextrelease-0.7.5.dist-info/WHEEL
gitnextrelease-0.7.5.dist-info/entry_points.txt
gitnextrelease-0.7.5.dist-info/RECORD
