Metadata-Version: 2.3
Name: gitnextrelease
Version: 0.7.5
Summary: a git release/feature/fix branch management cli
Author: Joe
Author-email: joe@sunset-crew.com
Requires-Python: >=3.10,<4.0
Classifier: Programming Language :: Python :: 3
Classifier: Programming Language :: Python :: 3.10
Classifier: Programming Language :: Python :: 3.11
Classifier: Programming Language :: Python :: 3.12
Classifier: Programming Language :: Python :: 3.13
Requires-Dist: setuptools (>=69.1.1,<70.0.0)
